{
  "id": "9ac713e923f106319f685c6465f1b30fc60159e5",
  "url": "https://www.r-bloggers.com/2023/11/empowering-open-science-donate-to-support-our-mission/",
  "created_at_utc": "2025-11-17T20:39:11Z",
  "data": null,
  "raw_original": {
    "uuid": "589adc3a-6d4f-4f7f-a913-9b868df3cb2b",
    "created_at": "2025-11-17 20:39:11",
    "raw_json": {
      "article_author": null,
      "article_headline": null,
      "article_modified": null,
      "article_published": null,
      "article_section": null,
      "article_tags": null,
      "canonical_url": "https://www.r-bloggers.com/2023/11/empowering-open-science-donate-to-support-our-mission/",
      "crawled_at": "2025-11-17T09:54:16.600127",
      "external_links": [
        {
          "href": "https://ropensci.org/blog/2023/11/21/donation-2023/",
          "text": "rOpenSci - open tools for open science"
        },
        {
          "href": "http://r-posts.com/",
          "text": "here"
        },
        {
          "href": "https://ropensci.org/r-universe/",
          "text": "R-Universe"
        },
        {
          "href": "https://ropensci.org/champions/",
          "text": "Champions Program"
        },
        {
          "href": "https://ropensci.org/multilingual-publishing/",
          "text": "publication of multilingual"
        },
        {
          "href": "https://ropensci.org/stat-software-review/",
          "text": "statistical"
        },
        {
          "href": "https://ropensci.org/software-review/",
          "text": "software peer review"
        },
        {
          "href": "https://contributing.ropensci.org/",
          "text": "Contributing Guide"
        },
        {
          "href": "https://ropensci.org/donate/",
          "text": "https://ropensci.org/donate/"
        },
        {
          "href": "https://ropensci.org/blog/2023/11/21/donation-2023/",
          "text": "rOpenSci - open tools for open science"
        },
        {
          "href": "https://feedburner.google.com/fb/a/mailverify?uri=RBloggers",
          "text": "daily e-mail updates"
        },
        {
          "href": "https://www.r-project.org/",
          "text": "R"
        },
        {
          "href": "https://www.r-users.com/",
          "text": "Click here if you're looking to post or find an R/data-science job"
        },
        {
          "href": "http://r-posts.com/",
          "text": "here"
        }
      ],
      "h1_title": "R-bloggers",
      "html_title": "Empowering Open Science: Donate to Support our Mission | R-bloggers",
      "images": [],
      "internal_links": [
        {
          "href": "https://www.r-bloggers.com/author/ropensci-open-tools-for-open-science/",
          "text": "rOpenSci - open tools for open science"
        },
        {
          "href": "https://www.r-bloggers.com/category/r-bloggers/",
          "text": "R bloggers"
        },
        {
          "href": "https://www.r-bloggers.com/",
          "text": "R-bloggers"
        },
        {
          "href": "https://www.r-bloggers.com/contact-us/",
          "text": "here"
        },
        {
          "href": "https://www.r-bloggers.com/add-your-blog/",
          "text": "click here"
        },
        {
          "href": "https://www.r-bloggers.com/",
          "text": "R-bloggers.com"
        },
        {
          "href": "https://www.r-bloggers.com/how-to-learn-r-2/",
          "text": "learning R"
        },
        {
          "href": "https://www.r-bloggers.com/add-your-blog/",
          "text": "click here"
        }
      ],
      "lang": "en-US",
      "main_html": "<article class=\"post-380216 post type-post status-publish format-standard hentry category-r-bloggers\">\n<header class=\"post-header\">\n<h1 class=\"entry-title\">Empowering Open Science: Donate to Support our Mission</h1>\n<p class=\"meta post-meta\">Posted on <span class=\"updated\">November 20, 2023</span>  by <span class=\"vcard author\"><a class=\"fn\" href=\"https://www.r-bloggers.com/author/ropensci-open-tools-for-open-science/\">rOpenSci - open tools for open science</a></span>  in <a href=\"https://www.r-bloggers.com/category/r-bloggers/\" rel=\"category tag\">R bloggers</a> | 0 Comments</p>\n</header>\n<div class=\"entry clearfix\">\n<!-- \r\n<div style=\"min-height: 30px;\">\r\n[social4i size=\"small\" align=\"align-left\"]\r\n</div>\r\n-->\n<div style=\"border: 1px solid; background: none repeat scroll 0 0 #EDEDED; margin: 1px; font-size: 12px;\">\r\n[This article was first published on  <strong><a href=\"https://ropensci.org/blog/2023/11/21/donation-2023/\"> rOpenSci - open tools for open science</a></strong>, and kindly contributed to <a href=\"https://www.r-bloggers.com/\" rel=\"nofollow\">R-bloggers</a>].  (You can report issue about the content on this page <a href=\"https://www.r-bloggers.com/contact-us/\">here</a>)\r\n<hr/>Want to share your content on R-bloggers?<a href=\"https://www.r-bloggers.com/add-your-blog/\" rel=\"nofollow\"> click here</a> if you have a blog, or <a href=\"http://r-posts.com/\" rel=\"nofollow\"> here</a> if you don't.\r\n</div>\n\n<!-- Share buttons by mashshare.net - Version: 3.8.9-->\n<p>rOpenSci is a nonprofit organization that is funded entirely by grants and donations. These contributions enable us to keep our projects and infrastructure active and accessible to the community.</p>\n<p>Our projects are dedicated to establishing and upholding both technical and social infrastructure that supports open and reproducible science for all our members. This means our efforts must be sustainable, inclusive, and created collaboratively by and for all groups.</p>\n<p>Each action taken by rOpenSci seeks to break down barriers to accessing knowledge in the drive to democratize access to quality resources. Examples are the <a href=\"https://ropensci.org/r-universe/\" rel=\"nofollow\" target=\"_blank\">R-Universe</a>, the <a href=\"https://ropensci.org/champions/\" rel=\"nofollow\" target=\"_blank\">Champions Program</a>, and the <a href=\"https://ropensci.org/multilingual-publishing/\" rel=\"nofollow\" target=\"_blank\">publication of multilingual</a> resources. We also strive to transform science by creating processes and building capacity to ensure software quality and good practices, for example, our (<a href=\"https://ropensci.org/stat-software-review/\" rel=\"nofollow\" target=\"_blank\">statistical</a>) <a href=\"https://ropensci.org/software-review/\" rel=\"nofollow\" target=\"_blank\">software peer review</a>.</p>\n<p>Sustaining an open project with quality infrastructure freely accessible to the global and diverse community of R software users, research software developers, and engineers requires many different resources. Our organization’s ongoing costs are supported by grants and donations from individuals and organizations which share our vision and mission.</p>\n<p>By supporting us, you’re not just donating; you’re contributing to a community that’s breaking down barriers, creating opportunities, and shaping the future of open and reproducible science for everyone. Join us in this vital mission today!</p>\n<h2>\nBeing part of the community\n</h2><p>The concept of community gives meaning to rOpenSci’s work and it is within this framework that we develop projects. Therefore, it is natural for us to look to the community to help us move forward.</p>\n<p>Every little bit helps. That is why we invite you to collaborate with us or to share this information with any people or organizations that you think may be interested.</p>\n<p>You can also support us by participating in our projects and activities. Check out our <a href=\"https://contributing.ropensci.org/\" rel=\"nofollow\" target=\"_blank\">Contributing Guide</a> which covers all the ways you can get more involved with rOpenSci and how you may benefit. 😄</p>\n<h2>\nDonate to rOpenSci\n</h2><p>rOpenSci is a project sponsored by NumFOCUS, a U.S. 501(c)(3) non-profit charitable organization.</p>\n<p>You can donate here: <a href=\"https://ropensci.org/donate/\" rel=\"nofollow\" target=\"_blank\">https://ropensci.org/donate/</a></p>\n<p>Thank you for helping us to keep rOpenSci active! 🙏</p>\n<div class=\"jp-relatedposts\" id=\"jp-relatedposts\">\n<h3 class=\"jp-relatedposts-headline\"><em>Related</em></h3>\n</div>\n<!-- Share buttons by mashshare.net - Version: 3.8.9-->\n<div style=\"border: 1px solid; background: none repeat scroll 0 0 #EDEDED; margin: 1px; font-size: 13px;\">\n<div style=\"text-align: center;\">To <strong>leave a comment</strong> for the author, please follow the link and comment on their blog: <strong><a href=\"https://ropensci.org/blog/2023/11/21/donation-2023/\"> rOpenSci - open tools for open science</a></strong>.</div>\n<hr>\n<a href=\"https://www.r-bloggers.com/\" rel=\"nofollow\">R-bloggers.com</a> offers <strong><a href=\"https://feedburner.google.com/fb/a/mailverify?uri=RBloggers\" rel=\"nofollow\">daily e-mail updates</a></strong> about <a href=\"https://www.r-project.org/\" rel=\"nofollow\" title=\"The R Project for Statistical Computing\">R</a> news and tutorials about <a href=\"https://www.r-bloggers.com/how-to-learn-r-2/\" rel=\"nofollow\" title=\"R tutorials\">learning R</a> and many other topics. <a href=\"https://www.r-users.com/\" rel=\"nofollow\" title=\"Data science jobs\">Click here if you're looking to post or find an R/data-science job</a>.\r\n\r\n<hr/>Want to share your content on R-bloggers?<a href=\"https://www.r-bloggers.com/add-your-blog/\" rel=\"nofollow\"> click here</a> if you have a blog, or <a href=\"http://r-posts.com/\" rel=\"nofollow\"> here</a> if you don't.\r\n</hr></div> </div>\n</article>",
      "main_text": "Empowering Open Science: Donate to Support our Mission\nPosted on\nNovember 20, 2023\nby\nrOpenSci - open tools for open science\nin\nR bloggers\n| 0 Comments\n[This article was first published on\nrOpenSci - open tools for open science\n, and kindly contributed to\nR-bloggers\n].  (You can report issue about the content on this page\nhere\n)\nWant to share your content on R-bloggers?\nclick here\nif you have a blog, or\nhere\nif you don't.\nrOpenSci is a nonprofit organization that is funded entirely by grants and donations. These contributions enable us to keep our projects and infrastructure active and accessible to the community.\nOur projects are dedicated to establishing and upholding both technical and social infrastructure that supports open and reproducible science for all our members. This means our efforts must be sustainable, inclusive, and created collaboratively by and for all groups.\nEach action taken by rOpenSci seeks to break down barriers to accessing knowledge in the drive to democratize access to quality resources. Examples are the\nR-Universe\n, the\nChampions Program\n, and the\npublication of multilingual\nresources. We also strive to transform science by creating processes and building capacity to ensure software quality and good practices, for example, our (\nstatistical\n)\nsoftware peer review\n.\nSustaining an open project with quality infrastructure freely accessible to the global and diverse community of R software users, research software developers, and engineers requires many different resources. Our organization’s ongoing costs are supported by grants and donations from individuals and organizations which share our vision and mission.\nBy supporting us, you’re not just donating; you’re contributing to a community that’s breaking down barriers, creating opportunities, and shaping the future of open and reproducible science for everyone. Join us in this vital mission today!\nBeing part of the community\nThe concept of community gives meaning to rOpenSci’s work and it is within this framework that we develop projects. Therefore, it is natural for us to look to the community to help us move forward.\nEvery little bit helps. That is why we invite you to collaborate with us or to share this information with any people or organizations that you think may be interested.\nYou can also support us by participating in our projects and activities. Check out our\nContributing Guide\nwhich covers all the ways you can get more involved with rOpenSci and how you may benefit. 😄\nDonate to rOpenSci\nrOpenSci is a project sponsored by NumFOCUS, a U.S. 501(c)(3) non-profit charitable organization.\nYou can donate here:\nhttps://ropensci.org/donate/\nThank you for helping us to keep rOpenSci active! 🙏\nRelated\nTo\nleave a comment\nfor the author, please follow the link and comment on their blog:\nrOpenSci - open tools for open science\n.\nR-bloggers.com\noffers\ndaily e-mail updates\nabout\nR\nnews and tutorials about\nlearning R\nand many other topics.\nClick here if you're looking to post or find an R/data-science job\n.\nWant to share your content on R-bloggers?\nclick here\nif you have a blog, or\nhere\nif you don't.",
      "meta_description": "rOpenSci is a nonprofit organization that is funded entirely by grants and donations. These contributions enable us to keep our projects and infrastructure active and accessible to the community. Our projects are dedicated to establishing and upholdin...",
      "meta_keywords": null,
      "og_description": "rOpenSci is a nonprofit organization that is funded entirely by grants and donations. These contributions enable us to keep our projects and infrastructure active and accessible to the community. Our projects are dedicated to establishing and upholdin...",
      "og_image": "https://www.r-bloggers.com/wp-content/uploads/2016/04/R_02_2016-05-01.png",
      "og_title": "Empowering Open Science: Donate to Support our Mission | R-bloggers",
      "raw_jsonld_article": null,
      "reading_time_min": 2.6,
      "sitemap_lastmod": "2023-11-21T00:00:00+00:00",
      "twitter_description": "rOpenSci is a nonprofit organization that is funded entirely by grants and donations. These contributions enable us to keep our projects and infrastructure active and accessible to the community. Our projects are dedicated to establishing and upholdin...",
      "twitter_title": "Empowering Open Science: Donate to Support our Mission | R-bloggers",
      "url": "https://www.r-bloggers.com/2023/11/empowering-open-science-donate-to-support-our-mission/",
      "word_count": 514
    }
  }
}