{
  "uuid": "e99406e7-13e1-422a-a7a1-604fc537c0c7",
  "created_at": "2025-11-22 19:59:33",
  "raw_json": {
    "article_author": null,
    "article_headline": null,
    "article_modified": null,
    "article_published": null,
    "article_section": null,
    "article_tags": null,
    "canonical_url": "https://www.r-bloggers.com/2024/12/creating-an-animated-christmas-tree-in-r/",
    "crawled_at": "2025-11-22T10:56:19.475186",
    "external_links": [
      {
        "href": "https://www.jumpingrivers.com/blog/christmas-tree/",
        "text": "The Jumping Rivers Blog"
      },
      {
        "href": "http://r-posts.com/",
        "text": "here"
      },
      {
        "href": "https://www.jumpingrivers.com/blog/christmas-tree/",
        "text": null
      },
      {
        "href": "https://ggplot2.tidyverse.org/",
        "text": "{ggplot2}"
      },
      {
        "href": "https://r-spatial.github.io/sf/",
        "text": "{sf}"
      },
      {
        "href": "https://gganimate.com/",
        "text": "{gganimate}"
      },
      {
        "href": "https://www.jumpingrivers.com/blog/christmas-tree/",
        "text": "original post"
      },
      {
        "href": "https://www.jumpingrivers.com/blog/christmas-tree/",
        "text": "The Jumping Rivers Blog"
      },
      {
        "href": "https://feedburner.google.com/fb/a/mailverify?uri=RBloggers",
        "text": "daily e-mail updates"
      },
      {
        "href": "https://www.r-project.org/",
        "text": "R"
      },
      {
        "href": "https://www.r-users.com/",
        "text": "Click here if you're looking to post or find an R/data-science job"
      },
      {
        "href": "http://r-posts.com/",
        "text": "here"
      }
    ],
    "h1_title": "R-bloggers",
    "html_title": "Creating an animated Christmas tree in R | R-bloggers",
    "images": [
      {
        "alt": null,
        "base64": "data:image/gif;base64,R0lGODlhAQABAIAAAAAAAP///yH5BAEAAAAALAAAAAABAAEAAAIBRAA7",
        "src": "https://www.r-bloggers.com/wp-content/plugins/jetpack/modules/lazy-images/images/1x1.trans.gif"
      },
      {
        "alt": null,
        "base64": null,
        "src": "https://i2.wp.com/www.jumpingrivers.com/blog/christmas-tree/featured.png?w=400&ssl=1"
      },
      {
        "alt": "Christmas tree shape made with the sf and Ggplot2 R packages.",
        "base64": "data:image/gif;base64,R0lGODlhAQABAIAAAAAAAP///yH5BAEAAAAALAAAAAABAAEAAAIBRAA7",
        "src": "https://www.r-bloggers.com/wp-content/plugins/jetpack/modules/lazy-images/images/1x1.trans.gif"
      },
      {
        "alt": "Christmas tree shape made with the sf and Ggplot2 R packages.",
        "base64": null,
        "src": "https://i1.wp.com/www.jumpingrivers.com/blog/christmas-tree/tree_shape.png?w=578&ssl=1"
      },
      {
        "alt": "Green Christmas tree made with the Ggplot2 R package.",
        "base64": "data:image/gif;base64,R0lGODlhAQABAIAAAAAAAP///yH5BAEAAAAALAAAAAABAAEAAAIBRAA7",
        "src": "https://www.r-bloggers.com/wp-content/plugins/jetpack/modules/lazy-images/images/1x1.trans.gif"
      },
      {
        "alt": "Green Christmas tree made with the Ggplot2 R package.",
        "base64": null,
        "src": "https://i0.wp.com/www.jumpingrivers.com/blog/christmas-tree/finished_tree.png?w=578&ssl=1"
      },
      {
        "alt": "Christmas tree with lights made with the sf and Ggplot2 R packages.",
        "base64": "data:image/gif;base64,R0lGODlhAQABAIAAAAAAAP///yH5BAEAAAAALAAAAAABAAEAAAIBRAA7",
        "src": "https://www.r-bloggers.com/wp-content/plugins/jetpack/modules/lazy-images/images/1x1.trans.gif"
      },
      {
        "alt": "Christmas tree with lights made with the sf and Ggplot2 R packages.",
        "base64": null,
        "src": "https://i0.wp.com/www.jumpingrivers.com/blog/christmas-tree/tree_lights.png?w=578&ssl=1"
      },
      {
        "alt": "Final Christmas tree GIF with sparkling lights.",
        "base64": "data:image/gif;base64,R0lGODlhAQABAIAAAAAAAP///yH5BAEAAAAALAAAAAABAAEAAAIBRAA7",
        "src": "https://www.r-bloggers.com/wp-content/plugins/jetpack/modules/lazy-images/images/1x1.trans.gif"
      },
      {
        "alt": "Final Christmas tree GIF with sparkling lights.",
        "base64": null,
        "src": "https://i1.wp.com/www.jumpingrivers.com/blog/christmas-tree/twinkling_christmas_tree.gif?w=578&ssl=1"
      }
    ],
    "internal_links": [
      {
        "href": "https://www.r-bloggers.com/author/the-jumping-rivers-blog/",
        "text": "The Jumping Rivers Blog"
      },
      {
        "href": "https://www.r-bloggers.com/category/r-bloggers/",
        "text": "R bloggers"
      },
      {
        "href": "https://www.r-bloggers.com/",
        "text": "R-bloggers"
      },
      {
        "href": "https://www.r-bloggers.com/contact-us/",
        "text": "here"
      },
      {
        "href": "https://www.r-bloggers.com/add-your-blog/",
        "text": "click here"
      },
      {
        "href": "https://www.r-bloggers.com/",
        "text": "R-bloggers.com"
      },
      {
        "href": "https://www.r-bloggers.com/how-to-learn-r-2/",
        "text": "learning R"
      },
      {
        "href": "https://www.r-bloggers.com/add-your-blog/",
        "text": "click here"
      }
    ],
    "lang": "en-US",
    "main_html": "<article class=\"post-389459 post type-post status-publish format-standard hentry category-r-bloggers\">\n<header class=\"post-header\">\n<h1 class=\"entry-title\">Creating an animated Christmas tree in R</h1>\n<p class=\"meta post-meta\">Posted on <span class=\"updated\">December 24, 2024</span>  by <span class=\"vcard author\"><a class=\"fn\" href=\"https://www.r-bloggers.com/author/the-jumping-rivers-blog/\">The Jumping Rivers Blog</a></span>  in <a href=\"https://www.r-bloggers.com/category/r-bloggers/\" rel=\"category tag\">R bloggers</a> | 0 Comments</p>\n</header>\n<div class=\"entry clearfix\">\n<!-- \n<div style=\"min-height: 30px;\">\n[social4i size=\"small\" align=\"align-left\"]\n</div>\n-->\n<div style=\"border: 1px solid; background: none repeat scroll 0 0 #EDEDED; margin: 1px; font-size: 12px;\">\n[This article was first published on  <strong><a href=\"https://www.jumpingrivers.com/blog/christmas-tree/\"> The Jumping Rivers Blog</a></strong>, and kindly contributed to <a href=\"https://www.r-bloggers.com/\" rel=\"nofollow\">R-bloggers</a>].  (You can report issue about the content on this page <a href=\"https://www.r-bloggers.com/contact-us/\">here</a>)\n<hr/>Want to share your content on R-bloggers?<a href=\"https://www.r-bloggers.com/add-your-blog/\" rel=\"nofollow\"> click here</a> if you have a blog, or <a href=\"http://r-posts.com/\" rel=\"nofollow\"> here</a> if you don't.\n</div>\n\n<!-- Share buttons by mashshare.net - Version: 4.0.47-->\n<p>\n<a href=\"https://www.jumpingrivers.com/blog/christmas-tree/\">\n<img class=\"image-center\" data-lazy-src=\"https://i2.wp.com/www.jumpingrivers.com/blog/christmas-tree/featured.png?w=400&amp;ssl=1\" data-recalc-dims=\"1\" src=\"https://www.r-bloggers.com/wp-content/plugins/jetpack/modules/lazy-images/images/1x1.trans.gif\" style=\"width:400px\"/><noscript><img class=\"image-center\" data-recalc-dims=\"1\" src=\"https://i2.wp.com/www.jumpingrivers.com/blog/christmas-tree/featured.png?w=400&amp;ssl=1\" style=\"width:400px\"/></noscript>\n</a>\n</p>\n<p>With Christmas tomorrow we have decided to create an animated Christmas\nTree using <a href=\"https://ggplot2.tidyverse.org/\" rel=\"nofollow\" target=\"_blank\">{ggplot2}</a>,\n<a href=\"https://r-spatial.github.io/sf/\" rel=\"nofollow\" target=\"_blank\">{sf}</a> and\n<a href=\"https://gganimate.com/\" rel=\"nofollow\" target=\"_blank\">{gganimate}</a>.</p>\n<p>First we need a tree. To do this we have used an {sf} polygon where we\npass in the coordinates of the Christmas tree as a list matrix to\n<code>st_polygon</code>. We can then use <code>geom_sf</code> to add this layer onto a ggplot\nobject.</p>\n<pre>library(ggplot2)\nlibrary(gganimate)\nlibrary(sf)\n\ntree_coords =\n list(\n matrix(\n c(-4, 0,\n -2.22, 2,\n -3.5, 2,\n -1.5, 4,\n -2.5, 4,\n -0.8, 6,\n -1.5, 6,\n 0, 8,\n 1.5, 6,\n 0.8, 6,\n 2.5, 4,\n 1.5, 4,\n 3.5, 2,\n 2.22, 2,\n 4, 0,\n -4, 0),\n ncol=2, byrow=T\n )\n )\n\ntree = st_polygon(tree_coords)\n\ngg_tree = ggplot() +\n geom_sf(aes(), data=tree)\n\ngg_tree\n</pre><img alt=\"Christmas tree shape made with the sf and Ggplot2 R packages.\" class=\"image-center\" data-lazy-src=\"https://i1.wp.com/www.jumpingrivers.com/blog/christmas-tree/tree_shape.png?w=578&amp;ssl=1\" data-recalc-dims=\"1\" src=\"https://www.r-bloggers.com/wp-content/plugins/jetpack/modules/lazy-images/images/1x1.trans.gif\" style=\"width: 450px;\"/><noscript><img alt=\"Christmas tree shape made with the sf and Ggplot2 R packages.\" class=\"image-center\" data-recalc-dims=\"1\" src=\"https://i1.wp.com/www.jumpingrivers.com/blog/christmas-tree/tree_shape.png?w=578&amp;ssl=1\" style=\"width: 450px;\"/></noscript>\n<p>Okay, so now we have a tree shape. Now we need to make it a little more\nChristmassy by changing:</p>\n<ul>\n<li>The color using: <code>fill = \"forestgreen\", color = \"darkgreen\"</code></li>\n<li>Adding the trunk:\n<code>geom_rect(aes(xmin = -0.75, xmax = 0.75, ymin = -2, ymax = 0), fill = \"saddlebrown\", color = \"sienna4\")</code></li>\n<li>Add a star on the top:\n<code>geom_point(aes(x = 0, y = 8), color = \"gold\", shape = 8, size = 7, stroke = 3)</code></li>\n<li>Remove the axis with: <code>theme_void()</code></li>\n<li>Set the border: <code>coord_sf(xlim = c(-6, 6), ylim = c(-4, 10))</code></li>\n<li>Add a Christmas message:\n<code>annotate(\"text\", x = 0, y = 9.5, label = \"Merry Christmas \\n From Jumping Rivers!\", size = 6)</code></li>\n</ul>\n<p>Now our tree looks like this:</p>\n<pre>gg_tree = ggplot() +\n geom_sf(aes(), data=tree, fill = \"forestgreen\", color = \"darkgreen\") +\n geom_rect(aes(xmin = -0.75, xmax = 0.75, ymin = -2, ymax = 0), fill = \"saddlebrown\", color = \"sienna4\") +\n geom_point(aes(x = 0, y = 8), color = \"gold\", shape = 8, size = 7, stroke = 3) +\n theme_void() +\n coord_sf(xlim = c(-6, 6), ylim = c(-4, 10)) +\n annotate(\"text\", x = 0, y = 9.5, label = \"Merry Christmas \\n From Jumping Rivers!\", size = 6)\n\ngg_tree\n</pre><img alt=\"Green Christmas tree made with the Ggplot2 R package.\" class=\"image-center\" data-lazy-src=\"https://i0.wp.com/www.jumpingrivers.com/blog/christmas-tree/finished_tree.png?w=578&amp;ssl=1\" data-recalc-dims=\"1\" src=\"https://www.r-bloggers.com/wp-content/plugins/jetpack/modules/lazy-images/images/1x1.trans.gif\" style=\"width: 450px;\"/><noscript><img alt=\"Green Christmas tree made with the Ggplot2 R package.\" class=\"image-center\" data-recalc-dims=\"1\" src=\"https://i0.wp.com/www.jumpingrivers.com/blog/christmas-tree/finished_tree.png?w=578&amp;ssl=1\" style=\"width: 450px;\"/></noscript>\n<p>Next we need to use {sf} again to make some lights for the tree then\n{gganimate} to make the lights flash.</p>\n<p>Placing the points within the boundaries of the tree was a trickier task\nthan we expected until we fell upon <code>st_sample</code> which we can pass a\npolygon to and it’ll create some sample points within the boundaries. We\nalso create a vector to colour the points.</p>\n<pre>points = st_sample(tree, 75)\ncolours = sample(c(\"red\", \"yellow\", \"blue\"), 75, replace = TRUE)\n\ngg_tree = ggplot() +\n geom_sf(aes(), data=tree, fill = \"forestgreen\", color = \"darkgreen\") +\n geom_sf(aes(), data=points, color = colours) +\n geom_rect(aes(xmin = -0.75, xmax = 0.75, ymin = -2, ymax = 0), fill = \"saddlebrown\", color = \"sienna4\") +\n geom_point(aes(x = 0, y = 8), color = \"gold\", shape = 8, size = 7, stroke = 3) +\n theme_void() +\n coord_sf(xlim = c(-6, 6), ylim = c(-4, 10)) +\n annotate(\"text\", x = 0, y = 9.5, label = \"Merry Christmas \\n From Jumping Rivers!\", size = 6)\n\ngg_tree\n</pre><img alt=\"Christmas tree with lights made with the sf and Ggplot2 R packages.\" class=\"image-center\" data-lazy-src=\"https://i0.wp.com/www.jumpingrivers.com/blog/christmas-tree/tree_lights.png?w=578&amp;ssl=1\" data-recalc-dims=\"1\" src=\"https://www.r-bloggers.com/wp-content/plugins/jetpack/modules/lazy-images/images/1x1.trans.gif\" style=\"width: 450px;\"/><noscript><img alt=\"Christmas tree with lights made with the sf and Ggplot2 R packages.\" class=\"image-center\" data-recalc-dims=\"1\" src=\"https://i0.wp.com/www.jumpingrivers.com/blog/christmas-tree/tree_lights.png?w=578&amp;ssl=1\" style=\"width: 450px;\"/></noscript>\n<p>We can now animate it to make the lights sparkle using <code>transition_time</code>\nand <code>ease_aes</code>:</p>\n<pre>gg_tree +\n transition_time(1:75) +\n ease_aes('linear')\n</pre><img alt=\"Final Christmas tree GIF with sparkling lights.\" class=\"image-center\" data-lazy-src=\"https://i1.wp.com/www.jumpingrivers.com/blog/christmas-tree/twinkling_christmas_tree.gif?w=578&amp;ssl=1\" data-recalc-dims=\"1\" src=\"https://www.r-bloggers.com/wp-content/plugins/jetpack/modules/lazy-images/images/1x1.trans.gif\" style=\"width: 450px;\"/><noscript><img alt=\"Final Christmas tree GIF with sparkling lights.\" class=\"image-center\" data-recalc-dims=\"1\" src=\"https://i1.wp.com/www.jumpingrivers.com/blog/christmas-tree/twinkling_christmas_tree.gif?w=578&amp;ssl=1\" style=\"width: 450px;\"/></noscript>\n<p>Lastly, have a great Christmas and New Year from the Jumping Rivers\nteam!</p>\n<p>\nFor updates and revisions to this article, see the <a href=\"https://www.jumpingrivers.com/blog/christmas-tree/\">original post</a>\n</p>\n<div class=\"jp-relatedposts\" id=\"jp-relatedposts\">\n<h3 class=\"jp-relatedposts-headline\"><em>Related</em></h3>\n</div>\n<!-- Share buttons by mashshare.net - Version: 4.0.47-->\n<div style=\"border: 1px solid; background: none repeat scroll 0 0 #EDEDED; margin: 1px; font-size: 13px;\">\n<div style=\"text-align: center;\">To <strong>leave a comment</strong> for the author, please follow the link and comment on their blog: <strong><a href=\"https://www.jumpingrivers.com/blog/christmas-tree/\"> The Jumping Rivers Blog</a></strong>.</div>\n<hr/>\n<a href=\"https://www.r-bloggers.com/\" rel=\"nofollow\">R-bloggers.com</a> offers <strong><a href=\"https://feedburner.google.com/fb/a/mailverify?uri=RBloggers\" rel=\"nofollow\">daily e-mail updates</a></strong> about <a href=\"https://www.r-project.org/\" rel=\"nofollow\" title=\"The R Project for Statistical Computing\">R</a> news and tutorials about <a href=\"https://www.r-bloggers.com/how-to-learn-r-2/\" rel=\"nofollow\" title=\"R tutorials\">learning R</a> and many other topics. <a href=\"https://www.r-users.com/\" rel=\"nofollow\" title=\"Data science jobs\">Click here if you're looking to post or find an R/data-science job</a>.\n\n<hr/>Want to share your content on R-bloggers?<a href=\"https://www.r-bloggers.com/add-your-blog/\" rel=\"nofollow\"> click here</a> if you have a blog, or <a href=\"http://r-posts.com/\" rel=\"nofollow\"> here</a> if you don't.\n</div> </div>\n</article>",
    "main_text": "Creating an animated Christmas tree in R\nPosted on\nDecember 24, 2024\nby\nThe Jumping Rivers Blog\nin\nR bloggers\n| 0 Comments\n[This article was first published on\nThe Jumping Rivers Blog\n, and kindly contributed to\nR-bloggers\n].  (You can report issue about the content on this page\nhere\n)\nWant to share your content on R-bloggers?\nclick here\nif you have a blog, or\nhere\nif you don't.\nWith Christmas tomorrow we have decided to create an animated Christmas\nTree using\n{ggplot2}\n,\n{sf}\nand\n{gganimate}\n.\nFirst we need a tree. To do this we have used an {sf} polygon where we\npass in the coordinates of the Christmas tree as a list matrix to\nst_polygon\n. We can then use\ngeom_sf\nto add this layer onto a ggplot\nobject.\nlibrary(ggplot2)\nlibrary(gganimate)\nlibrary(sf)\n\ntree_coords =\n list(\n matrix(\n c(-4, 0,\n -2.22, 2,\n -3.5, 2,\n -1.5, 4,\n -2.5, 4,\n -0.8, 6,\n -1.5, 6,\n 0, 8,\n 1.5, 6,\n 0.8, 6,\n 2.5, 4,\n 1.5, 4,\n 3.5, 2,\n 2.22, 2,\n 4, 0,\n -4, 0),\n ncol=2, byrow=T\n )\n )\n\ntree = st_polygon(tree_coords)\n\ngg_tree = ggplot() +\n geom_sf(aes(), data=tree)\n\ngg_tree\nOkay, so now we have a tree shape. Now we need to make it a little more\nChristmassy by changing:\nThe color using:\nfill = \"forestgreen\", color = \"darkgreen\"\nAdding the trunk:\ngeom_rect(aes(xmin = -0.75, xmax = 0.75, ymin = -2, ymax = 0), fill = \"saddlebrown\", color = \"sienna4\")\nAdd a star on the top:\ngeom_point(aes(x = 0, y = 8), color = \"gold\", shape = 8, size = 7, stroke = 3)\nRemove the axis with:\ntheme_void()\nSet the border:\ncoord_sf(xlim = c(-6, 6), ylim = c(-4, 10))\nAdd a Christmas message:\nannotate(\"text\", x = 0, y = 9.5, label = \"Merry Christmas \\n From Jumping Rivers!\", size = 6)\nNow our tree looks like this:\ngg_tree = ggplot() +\n geom_sf(aes(), data=tree, fill = \"forestgreen\", color = \"darkgreen\") +\n geom_rect(aes(xmin = -0.75, xmax = 0.75, ymin = -2, ymax = 0), fill = \"saddlebrown\", color = \"sienna4\") +\n geom_point(aes(x = 0, y = 8), color = \"gold\", shape = 8, size = 7, stroke = 3) +\n theme_void() +\n coord_sf(xlim = c(-6, 6), ylim = c(-4, 10)) +\n annotate(\"text\", x = 0, y = 9.5, label = \"Merry Christmas \\n From Jumping Rivers!\", size = 6)\n\ngg_tree\nNext we need to use {sf} again to make some lights for the tree then\n{gganimate} to make the lights flash.\nPlacing the points within the boundaries of the tree was a trickier task\nthan we expected until we fell upon\nst_sample\nwhich we can pass a\npolygon to and it’ll create some sample points within the boundaries. We\nalso create a vector to colour the points.\npoints = st_sample(tree, 75)\ncolours = sample(c(\"red\", \"yellow\", \"blue\"), 75, replace = TRUE)\n\ngg_tree = ggplot() +\n geom_sf(aes(), data=tree, fill = \"forestgreen\", color = \"darkgreen\") +\n geom_sf(aes(), data=points, color = colours) +\n geom_rect(aes(xmin = -0.75, xmax = 0.75, ymin = -2, ymax = 0), fill = \"saddlebrown\", color = \"sienna4\") +\n geom_point(aes(x = 0, y = 8), color = \"gold\", shape = 8, size = 7, stroke = 3) +\n theme_void() +\n coord_sf(xlim = c(-6, 6), ylim = c(-4, 10)) +\n annotate(\"text\", x = 0, y = 9.5, label = \"Merry Christmas \\n From Jumping Rivers!\", size = 6)\n\ngg_tree\nWe can now animate it to make the lights sparkle using\ntransition_time\nand\nease_aes\n:\ngg_tree +\n transition_time(1:75) +\n ease_aes('linear')\nLastly, have a great Christmas and New Year from the Jumping Rivers\nteam!\nFor updates and revisions to this article, see the\noriginal post\nRelated\nTo\nleave a comment\nfor the author, please follow the link and comment on their blog:\nThe Jumping Rivers Blog\n.\nR-bloggers.com\noffers\ndaily e-mail updates\nabout\nR\nnews and tutorials about\nlearning R\nand many other topics.\nClick here if you're looking to post or find an R/data-science job\n.\nWant to share your content on R-bloggers?\nclick here\nif you have a blog, or\nhere\nif you don't.",
    "meta_description": "With Christmas tomorrow we have decided to create an animated Christmas Tree using {ggplot2}, {sf} and {gganimate}. First we need a tree. To do this we have used an {sf} polygon where we pass in the coordinates of the Christmas tree as a list matrix to st_polygon. We can then use geom_sf to add this layer onto a ggplot object. library(ggplot2) library(gganimate) library(sf) tree_coords = list( matrix( c(-4, 0, -2.22, 2, -3.5, 2, -1.5, 4, -2.5, 4, -0.8, 6, -1.5, 6, 0, 8, 1.5, 6, 0.8, 6, 2.5, 4, 1.5, 4, 3.5, 2, 2.22, 2, 4, 0, -4, 0), ncol=2, byrow=T ) ) tree = st_polygon(tree_coords) gg_tree = ggplot() + geom_sf(aes(), data=tree) gg_tree Okay, so now we have a tree shape. Now we need to make it a little more Christmassy by changing: The color using: fill = \"forestgreen\", color = \"darkgreen\" Adding the trunk: geom_rect(aes(xmin = -0.75, xmax = 0.75, ymin = -2, ymax = 0), fill = \"saddlebrown\", color = \"sienna4\") Add a star on the top: geom_point(aes(x = 0, y = 8), color = \"gold\", shape = 8, size = 7, stroke = 3) Remove the axis with: theme_void() Set the border: coord_sf(xlim = c(-6, 6), ylim = c(-4, 10)) Add a Christmas message: annotate(\"text\", x = 0, y = 9.5, label = \"Merry Christmas \\n From Jumping Rivers!\", size = 6) Now our tree looks like this: gg_tree = ggplot() + geom_sf(aes(), data=tree, fill = \"forestgreen\", color = \"darkgreen\") + geom_rect(aes(xmin = -0.75, xmax = 0.75, ymin = -2, ymax = 0), fill = \"saddlebrown\", color = \"sienna4\") + geom_point(aes(x = 0, y = 8), color = \"gold\", shape = 8, size = 7, stroke = 3) + theme_void() + coord_sf(xlim = c(-6, 6), ylim = c(-4, 10)) + annotate(\"text\", x = 0, y = 9.5, label = \"Merry Christmas \\n From Jumping Rivers!\", size = 6) gg_tree Next we need to use {sf} again to make some lights for the tree then {gganimate} to make the lights flash. Placing the points within the boundaries of the tree was a trickier task than we expected until we fell upon st_sample which we can pass a polygon to and it’ll create some sample points within the boundaries. We also create a vector to colour the points. points = st_sample(tree, 75) colours = sample(c(\"red\", \"yellow\", \"blue\"), 75, replace = TRUE) gg_tree = ggplot() + geom_sf(aes(), data=tree, fill = \"forestgreen\", color = \"darkgreen\") + geom_sf(aes(), data=points, color = colours) + geom_rect(aes(xmin = -0.75, xmax = 0.75, ymin = -2, ymax = 0), fill = \"saddlebrown\", color = \"sienna4\") + geom_point(aes(x = 0, y = 8), color = \"gold\", shape = 8, size = 7, stroke = 3) + theme_void() + coord_sf(xlim = c(-6, 6), ylim = c(-4, 10)) + annotate(\"text\", x = 0, y = 9.5, label = \"Merry Christmas \\n From Jumping Rivers!\", size = 6) gg_tree We can now animate it to make the lights sparkle using transition_time and ease_aes: gg_tree + transition_time(1:75) + ease_aes('linear') Lastly, have a great Christmas and New Year from the Jumping Rivers team! For updates and revisions to this article, see the original post",
    "meta_keywords": null,
    "og_description": "With Christmas tomorrow we have decided to create an animated Christmas Tree using {ggplot2}, {sf} and {gganimate}. First we need a tree. To do this we have used an {sf} polygon where we pass in the coordinates of the Christmas tree as a list matrix to st_polygon. We can then use geom_sf to add this layer onto a ggplot object. library(ggplot2) library(gganimate) library(sf) tree_coords = list( matrix( c(-4, 0, -2.22, 2, -3.5, 2, -1.5, 4, -2.5, 4, -0.8, 6, -1.5, 6, 0, 8, 1.5, 6, 0.8, 6, 2.5, 4, 1.5, 4, 3.5, 2, 2.22, 2, 4, 0, -4, 0), ncol=2, byrow=T ) ) tree = st_polygon(tree_coords) gg_tree = ggplot() + geom_sf(aes(), data=tree) gg_tree Okay, so now we have a tree shape. Now we need to make it a little more Christmassy by changing: The color using: fill = \"forestgreen\", color = \"darkgreen\" Adding the trunk: geom_rect(aes(xmin = -0.75, xmax = 0.75, ymin = -2, ymax = 0), fill = \"saddlebrown\", color = \"sienna4\") Add a star on the top: geom_point(aes(x = 0, y = 8), color = \"gold\", shape = 8, size = 7, stroke = 3) Remove the axis with: theme_void() Set the border: coord_sf(xlim = c(-6, 6), ylim = c(-4, 10)) Add a Christmas message: annotate(\"text\", x = 0, y = 9.5, label = \"Merry Christmas \\n From Jumping Rivers!\", size = 6) Now our tree looks like this: gg_tree = ggplot() + geom_sf(aes(), data=tree, fill = \"forestgreen\", color = \"darkgreen\") + geom_rect(aes(xmin = -0.75, xmax = 0.75, ymin = -2, ymax = 0), fill = \"saddlebrown\", color = \"sienna4\") + geom_point(aes(x = 0, y = 8), color = \"gold\", shape = 8, size = 7, stroke = 3) + theme_void() + coord_sf(xlim = c(-6, 6), ylim = c(-4, 10)) + annotate(\"text\", x = 0, y = 9.5, label = \"Merry Christmas \\n From Jumping Rivers!\", size = 6) gg_tree Next we need to use {sf} again to make some lights for the tree then {gganimate} to make the lights flash. Placing the points within the boundaries of the tree was a trickier task than we expected until we fell upon st_sample which we can pass a polygon to and it’ll create some sample points within the boundaries. We also create a vector to colour the points. points = st_sample(tree, 75) colours = sample(c(\"red\", \"yellow\", \"blue\"), 75, replace = TRUE) gg_tree = ggplot() + geom_sf(aes(), data=tree, fill = \"forestgreen\", color = \"darkgreen\") + geom_sf(aes(), data=points, color = colours) + geom_rect(aes(xmin = -0.75, xmax = 0.75, ymin = -2, ymax = 0), fill = \"saddlebrown\", color = \"sienna4\") + geom_point(aes(x = 0, y = 8), color = \"gold\", shape = 8, size = 7, stroke = 3) + theme_void() + coord_sf(xlim = c(-6, 6), ylim = c(-4, 10)) + annotate(\"text\", x = 0, y = 9.5, label = \"Merry Christmas \\n From Jumping Rivers!\", size = 6) gg_tree We can now animate it to make the lights sparkle using transition_time and ease_aes: gg_tree + transition_time(1:75) + ease_aes('linear') Lastly, have a great Christmas and New Year from the Jumping Rivers team! For updates and revisions to this article, see the original post",
    "og_image": "https://www.jumpingrivers.com/blog/christmas-tree/featured.png",
    "og_title": "Creating an animated Christmas tree in R | R-bloggers",
    "raw_jsonld_article": null,
    "reading_time_min": 3.2,
    "sitemap_lastmod": null,
    "twitter_description": "With Christmas tomorrow we have decided to create an animated Christmas Tree using {ggplot2}, {sf} and {gganimate}. First we need a tree. To do this we have used an {sf} polygon where we pass in the coordinates of the Christmas tree as a list matrix to st_polygon. We can then use geom_sf to add this layer onto a ggplot object. library(ggplot2) library(gganimate) library(sf) tree_coords = list( matrix( c(-4, 0, -2.22, 2, -3.5, 2, -1.5, 4, -2.5, 4, -0.8, 6, -1.5, 6, 0, 8, 1.5, 6, 0.8, 6, 2.5, 4, 1.5, 4, 3.5, 2, 2.22, 2, 4, 0, -4, 0), ncol=2, byrow=T ) ) tree = st_polygon(tree_coords) gg_tree = ggplot() + geom_sf(aes(), data=tree) gg_tree Okay, so now we have a tree shape. Now we need to make it a little more Christmassy by changing: The color using: fill = \"forestgreen\", color = \"darkgreen\" Adding the trunk: geom_rect(aes(xmin = -0.75, xmax = 0.75, ymin = -2, ymax = 0), fill = \"saddlebrown\", color = \"sienna4\") Add a star on the top: geom_point(aes(x = 0, y = 8), color = \"gold\", shape = 8, size = 7, stroke = 3) Remove the axis with: theme_void() Set the border: coord_sf(xlim = c(-6, 6), ylim = c(-4, 10)) Add a Christmas message: annotate(\"text\", x = 0, y = 9.5, label = \"Merry Christmas \\n From Jumping Rivers!\", size = 6) Now our tree looks like this: gg_tree = ggplot() + geom_sf(aes(), data=tree, fill = \"forestgreen\", color = \"darkgreen\") + geom_rect(aes(xmin = -0.75, xmax = 0.75, ymin = -2, ymax = 0), fill = \"saddlebrown\", color = \"sienna4\") + geom_point(aes(x = 0, y = 8), color = \"gold\", shape = 8, size = 7, stroke = 3) + theme_void() + coord_sf(xlim = c(-6, 6), ylim = c(-4, 10)) + annotate(\"text\", x = 0, y = 9.5, label = \"Merry Christmas \\n From Jumping Rivers!\", size = 6) gg_tree Next we need to use {sf} again to make some lights for the tree then {gganimate} to make the lights flash. Placing the points within the boundaries of the tree was a trickier task than we expected until we fell upon st_sample which we can pass a polygon to and it’ll create some sample points within the boundaries. We also create a vector to colour the points. points = st_sample(tree, 75) colours = sample(c(\"red\", \"yellow\", \"blue\"), 75, replace = TRUE) gg_tree = ggplot() + geom_sf(aes(), data=tree, fill = \"forestgreen\", color = \"darkgreen\") + geom_sf(aes(), data=points, color = colours) + geom_rect(aes(xmin = -0.75, xmax = 0.75, ymin = -2, ymax = 0), fill = \"saddlebrown\", color = \"sienna4\") + geom_point(aes(x = 0, y = 8), color = \"gold\", shape = 8, size = 7, stroke = 3) + theme_void() + coord_sf(xlim = c(-6, 6), ylim = c(-4, 10)) + annotate(\"text\", x = 0, y = 9.5, label = \"Merry Christmas \\n From Jumping Rivers!\", size = 6) gg_tree We can now animate it to make the lights sparkle using transition_time and ease_aes: gg_tree + transition_time(1:75) + ease_aes('linear') Lastly, have a great Christmas and New Year from the Jumping Rivers team! For updates and revisions to this article, see the original post",
    "twitter_title": "Creating an animated Christmas tree in R | R-bloggers",
    "url": "https://www.r-bloggers.com/2024/12/creating-an-animated-christmas-tree-in-r/",
    "word_count": 649
  }
}